cosmosis2cobaya/_base.py
cosmosis2cobaya/boltzmann.py
cosmosis2cobaya/extrapolate.py
cosmosis2cobaya/cmb_lensing/kappa_beam/kappa_beam.py
cosmosis2cobaya/cmb_lensing/kappa_ell_cut/kappa_ell_cut.py
cosmosis2cobaya/intrinsic_alignments/choose_ia/choose_ia_params.py
cosmosis2cobaya/intrinsic_alignments/tatt/tatt_interface.py
cosmosis2cobaya/likelihood/2pt/2pt_point_mass/2pt_point_mass.py
cosmosis2cobaya/likelihood/2pt/cosebis/simple_like.py
cosmosis2cobaya/likelihood/des-y3/shear_ratio/shear_ratio_likelihood.py
cosmosis2cobaya/number_density/correlated_priors/correlated_priors.py
cosmosis2cobaya/number_density/load_nz_fits/load_nz_fits.py
cosmosis2cobaya/number_density/photoz_bias/photoz_bias.py
cosmosis2cobaya/number_density/photoz_width/photoz_width.py
cosmosis2cobaya/shear/add_intrinsic/add_intrinsic.py
cosmosis2cobaya/shear/cl_to_xi_fullsky/cl_to_xi_interface.py
cosmosis2cobaya/shear/cosebis/cl_to_cosebis/cl_to_cosebis_interface.py
cosmosis2cobaya/shear/point_mass/add_gammat_point_mass.py
cosmosis2cobaya/shear/shear_bias/shear_m_bias.py
cosmosis2cobaya/structure/fast_pt/fast_pt_interface.py
cosmosis2cobaya/structure/magnification/add_magnification.py
cosmosis2cobaya/structure/projection/project_2d.py
cosmosis2cobaya-1.0.dist-info/LICENSE
cosmosis2cobaya-1.0.dist-info/METADATA
cosmosis2cobaya-1.0.dist-info/WHEEL
cosmosis2cobaya-1.0.dist-info/top_level.txt
cosmosis2cobaya-1.0.dist-info/RECORD
