Metadata-Version: 2.1
Name: cosmosis2cobaya
Version: 1.0
Author: Jun-Qian Jiang
Classifier: Programming Language :: Python :: 3
Classifier: License :: OSI Approved :: MIT License
Classifier: Operating System :: OS Independent
Requires-Python: >=3.9
License-File: LICENSE
Requires-Dist: numpy
Requires-Dist: cosmosis
Requires-Dist: cobaya >=3.5.1
